{
 "cells": [
  {
   "cell_type": "code",
   "execution_count": 1,
   "metadata": {},
   "outputs": [],
   "source": [
    "import inspect\n",
    "import hybridcuda"
   ]
  },
  {
   "cell_type": "code",
   "execution_count": 5,
   "metadata": {},
   "outputs": [
    {
     "data": {
      "text/plain": [
       "22268"
      ]
     },
     "execution_count": 5,
     "metadata": {},
     "output_type": "execute_result"
    }
   ],
   "source": [
    "import os;\n",
    "os.getpid()"
   ]
  },
  {
   "cell_type": "code",
   "execution_count": 6,
   "metadata": {},
   "outputs": [
    {
     "data": {
      "text/plain": [
       "['__doc__',\n",
       " '__file__',\n",
       " '__loader__',\n",
       " '__name__',\n",
       " '__package__',\n",
       " '__spec__',\n",
       " 'cudajitcode',\n",
       " 'disassemble',\n",
       " 'error',\n",
       " 'initcuda',\n",
       " 'inspect',\n",
       " 'launch',\n",
       " 'processfunction',\n",
       " 'processfunctionsource',\n",
       " 'processlambda',\n",
       " 'ptxlinkcode',\n",
       " 'version']"
      ]
     },
     "execution_count": 6,
     "metadata": {},
     "output_type": "execute_result"
    }
   ],
   "source": [
    "dir(hybridcuda)"
   ]
  },
  {
   "cell_type": "code",
   "execution_count": 11,
   "metadata": {},
   "outputs": [
    {
     "data": {
      "text/plain": [
       "42"
      ]
     },
     "execution_count": 11,
     "metadata": {},
     "output_type": "execute_result"
    }
   ],
   "source": [
    "hybridcuda.version()"
   ]
  },
  {
   "cell_type": "code",
   "execution_count": 2,
   "metadata": {},
   "outputs": [],
   "source": [
    "import hello_cudapython"
   ]
  },
  {
   "cell_type": "code",
   "execution_count": 3,
   "metadata": {},
   "outputs": [],
   "source": [
    "cures = hybridcuda.initcuda()"
   ]
  },
  {
   "cell_type": "code",
   "execution_count": 4,
   "metadata": {},
   "outputs": [
    {
     "data": {
      "text/plain": [
       "0"
      ]
     },
     "execution_count": 4,
     "metadata": {},
     "output_type": "execute_result"
    }
   ],
   "source": [
    "cures"
   ]
  },
  {
   "cell_type": "code",
   "execution_count": 31,
   "metadata": {},
   "outputs": [],
   "source": [
    "hc = hybridcuda.processfunction(hello_cudapython.kernel)"
   ]
  },
  {
   "cell_type": "code",
   "execution_count": 32,
   "metadata": {},
   "outputs": [],
   "source": [
    "hc = hybridcuda.cudajitcode(hc)"
   ]
  },
  {
   "cell_type": "code",
   "execution_count": 33,
   "metadata": {},
   "outputs": [],
   "source": [
    "hc = hybridcuda.ptxlinkcode(hc)"
   ]
  },
  {
   "cell_type": "code",
   "execution_count": 34,
   "metadata": {},
   "outputs": [],
   "source": [
    "import numpy as np"
   ]
  },
  {
   "cell_type": "code",
   "execution_count": 35,
   "metadata": {},
   "outputs": [],
   "source": [
    "a = np.ones(10)"
   ]
  },
  {
   "cell_type": "code",
   "execution_count": 36,
   "metadata": {},
   "outputs": [],
   "source": [
    "b = np.ones(10)"
   ]
  },
  {
   "cell_type": "code",
   "execution_count": 37,
   "metadata": {},
   "outputs": [],
   "source": [
    "c = np.zeros(10)"
   ]
  },
  {
   "cell_type": "code",
   "execution_count": 38,
   "metadata": {},
   "outputs": [],
   "source": [
    "hc = hybridcuda.launch(hc, 1,1,1, 1,1,1, 0,0,  10, a,b,c)"
   ]
  },
  {
   "cell_type": "code",
   "execution_count": 39,
   "metadata": {},
   "outputs": [
    {
     "data": {
      "text/plain": [
       "array([1., 1., 1., 1., 1., 1., 1., 1., 1., 1.])"
      ]
     },
     "execution_count": 39,
     "metadata": {},
     "output_type": "execute_result"
    }
   ],
   "source": [
    "a"
   ]
  },
  {
   "cell_type": "code",
   "execution_count": 40,
   "metadata": {},
   "outputs": [
    {
     "data": {
      "text/plain": [
       "array([1., 1., 1., 1., 1., 1., 1., 1., 1., 1.])"
      ]
     },
     "execution_count": 40,
     "metadata": {},
     "output_type": "execute_result"
    }
   ],
   "source": [
    "b"
   ]
  },
  {
   "cell_type": "code",
   "execution_count": 41,
   "metadata": {},
   "outputs": [
    {
     "data": {
      "text/plain": [
       "array([2., 2., 2., 2., 2., 2., 2., 2., 2., 2.])"
      ]
     },
     "execution_count": 41,
     "metadata": {},
     "output_type": "execute_result"
    }
   ],
   "source": [
    "c"
   ]
  },
  {
   "cell_type": "code",
   "execution_count": 42,
   "metadata": {},
   "outputs": [],
   "source": [
    "def addkernel(N : int, a, b, c):\n",
    "    for i in range(N):\n",
    "        c[i] = a[i] + b[i]"
   ]
  },
  {
   "cell_type": "code",
   "execution_count": 43,
   "metadata": {},
   "outputs": [],
   "source": [
    "hc = hybridcuda.processfunction(addkernel)"
   ]
  },
  {
   "cell_type": "code",
   "execution_count": 44,
   "metadata": {},
   "outputs": [
    {
     "data": {
      "text/plain": [
       "{'version': 42,\n",
       " 'cuda': '// GENERATED BY HYBRIDIZER/PYTHON \\n\\n#include <hybpython.cuh>\\n\\n// declare all functions -- prototypes \\n\\n// declare all functions -- implementations \\n\\n// declare global function \\nextern \"C\" \\n__global__ void addkernel (hybpython::pylong N , hybpython::thing a , hybpython::thing b , hybpython::thing c) \\n{\\n\\tfor ( hybpython::pylong  i = 0 ; i < ( N ) ; ++ i )\\n\\t{\\n\\thybpython::set_index < hybpython::thing , hybpython::pylong , hybpython::thing > ( c , i , hybpython::binary_op <hybpython::binaryops::add <hybpython::thing,hybpython::thing,hybpython::thing>>::eval <> ( hybpython::get_index < hybpython::thing , hybpython::pylong > ( a , i ) , hybpython::get_index < hybpython::thing , hybpython::pylong > ( b , i ) ) ) ;\\n\\t}\\n}\\n\\n',\n",
       " 'kernelname': 'addkernel',\n",
       " 'argtypes': ['hybpython::pylong',\n",
       "  'hybpython::thing',\n",
       "  'hybpython::thing',\n",
       "  'hybpython::thing']}"
      ]
     },
     "execution_count": 44,
     "metadata": {},
     "output_type": "execute_result"
    }
   ],
   "source": [
    "hc"
   ]
  },
  {
   "cell_type": "code",
   "execution_count": 45,
   "metadata": {},
   "outputs": [],
   "source": [
    "hc = hybridcuda.cudajitcode(hc)\n",
    "hc = hybridcuda.ptxlinkcode(hc)"
   ]
  },
  {
   "cell_type": "code",
   "execution_count": 46,
   "metadata": {},
   "outputs": [],
   "source": [
    "hc = hybridcuda.launch(hc, 1,1,1, 1,1,1, 0,0,  10, a,b,c)"
   ]
  },
  {
   "cell_type": "code",
   "execution_count": 47,
   "metadata": {},
   "outputs": [
    {
     "data": {
      "text/plain": [
       "array([2., 2., 2., 2., 2., 2., 2., 2., 2., 2.])"
      ]
     },
     "execution_count": 47,
     "metadata": {},
     "output_type": "execute_result"
    }
   ],
   "source": [
    "c"
   ]
  },
  {
   "cell_type": "code",
   "execution_count": 22,
   "metadata": {},
   "outputs": [],
   "source": [
    "c = np.zeros(10)"
   ]
  },
  {
   "cell_type": "code",
   "execution_count": 23,
   "metadata": {},
   "outputs": [
    {
     "data": {
      "text/plain": [
       "array([0., 0., 0., 0., 0., 0., 0., 0., 0., 0.])"
      ]
     },
     "execution_count": 23,
     "metadata": {},
     "output_type": "execute_result"
    }
   ],
   "source": [
    "c"
   ]
  },
  {
   "cell_type": "code",
   "execution_count": 24,
   "metadata": {},
   "outputs": [],
   "source": [
    "hc = hybridcuda.launch(hc, 1,1,1, 1,1,1, 0,0,  10, a,b,c)"
   ]
  },
  {
   "cell_type": "code",
   "execution_count": 25,
   "metadata": {},
   "outputs": [
    {
     "data": {
      "text/plain": [
       "array([2., 2., 2., 2., 2., 2., 2., 2., 2., 2.])"
      ]
     },
     "execution_count": 25,
     "metadata": {},
     "output_type": "execute_result"
    }
   ],
   "source": [
    "c"
   ]
  },
  {
   "cell_type": "code",
   "execution_count": null,
   "metadata": {},
   "outputs": [],
   "source": [
    "hc.cuda\n"
   ]
  },
  {
   "cell_type": "code",
   "execution_count": null,
   "metadata": {},
   "outputs": [],
   "source": []
  },
  {
   "cell_type": "code",
   "execution_count": 1,
   "metadata": {},
   "outputs": [
    {
     "data": {
      "text/plain": [
       "'a = func(lambda : 42)\\n'"
      ]
     },
     "execution_count": 1,
     "metadata": {},
     "output_type": "execute_result"
    }
   ],
   "source": [
    "import inspect\n",
    "\n",
    "def func(a): \n",
    "    return a;\n",
    "\n",
    "a = func(lambda : 42)\n",
    "\n",
    "z = a();\n",
    "\n",
    "inspect.getsource(a)"
   ]
  },
  {
   "cell_type": "code",
   "execution_count": 2,
   "metadata": {},
   "outputs": [
    {
     "data": {
      "text/plain": [
       "['ArgInfo',\n",
       " 'ArgSpec',\n",
       " 'Arguments',\n",
       " 'Attribute',\n",
       " 'BlockFinder',\n",
       " 'BoundArguments',\n",
       " 'CORO_CLOSED',\n",
       " 'CORO_CREATED',\n",
       " 'CORO_RUNNING',\n",
       " 'CORO_SUSPENDED',\n",
       " 'CO_ASYNC_GENERATOR',\n",
       " 'CO_COROUTINE',\n",
       " 'CO_GENERATOR',\n",
       " 'CO_ITERABLE_COROUTINE',\n",
       " 'CO_NESTED',\n",
       " 'CO_NEWLOCALS',\n",
       " 'CO_NOFREE',\n",
       " 'CO_OPTIMIZED',\n",
       " 'CO_VARARGS',\n",
       " 'CO_VARKEYWORDS',\n",
       " 'ClosureVars',\n",
       " 'EndOfBlock',\n",
       " 'FrameInfo',\n",
       " 'FullArgSpec',\n",
       " 'GEN_CLOSED',\n",
       " 'GEN_CREATED',\n",
       " 'GEN_RUNNING',\n",
       " 'GEN_SUSPENDED',\n",
       " 'OrderedDict',\n",
       " 'Parameter',\n",
       " 'Signature',\n",
       " 'TPFLAGS_IS_ABSTRACT',\n",
       " 'Traceback',\n",
       " '_ClassMethodWrapper',\n",
       " '_KEYWORD_ONLY',\n",
       " '_MethodWrapper',\n",
       " '_NonUserDefinedCallables',\n",
       " '_PARAM_NAME_MAPPING',\n",
       " '_POSITIONAL_ONLY',\n",
       " '_POSITIONAL_OR_KEYWORD',\n",
       " '_ParameterKind',\n",
       " '_VAR_KEYWORD',\n",
       " '_VAR_POSITIONAL',\n",
       " '_WrapperDescriptor',\n",
       " '__author__',\n",
       " '__builtins__',\n",
       " '__cached__',\n",
       " '__doc__',\n",
       " '__file__',\n",
       " '__loader__',\n",
       " '__name__',\n",
       " '__package__',\n",
       " '__spec__',\n",
       " '_check_class',\n",
       " '_check_instance',\n",
       " '_empty',\n",
       " '_filesbymodname',\n",
       " '_findclass',\n",
       " '_finddoc',\n",
       " '_get_paramkind_descr',\n",
       " '_getfullargs',\n",
       " '_is_type',\n",
       " '_main',\n",
       " '_missing_arguments',\n",
       " '_sentinel',\n",
       " '_shadowed_dict',\n",
       " '_signature_bound_method',\n",
       " '_signature_from_builtin',\n",
       " '_signature_from_callable',\n",
       " '_signature_from_function',\n",
       " '_signature_fromstr',\n",
       " '_signature_get_bound_param',\n",
       " '_signature_get_partial',\n",
       " '_signature_get_user_defined_method',\n",
       " '_signature_is_builtin',\n",
       " '_signature_is_functionlike',\n",
       " '_signature_strip_non_python_syntax',\n",
       " '_static_getmro',\n",
       " '_too_many',\n",
       " '_void',\n",
       " 'abc',\n",
       " 'ast',\n",
       " 'attrgetter',\n",
       " 'builtins',\n",
       " 'classify_class_attrs',\n",
       " 'cleandoc',\n",
       " 'collections',\n",
       " 'currentframe',\n",
       " 'dis',\n",
       " 'enum',\n",
       " 'findsource',\n",
       " 'formatannotation',\n",
       " 'formatannotationrelativeto',\n",
       " 'formatargspec',\n",
       " 'formatargvalues',\n",
       " 'functools',\n",
       " 'getabsfile',\n",
       " 'getargs',\n",
       " 'getargspec',\n",
       " 'getargvalues',\n",
       " 'getattr_static',\n",
       " 'getblock',\n",
       " 'getcallargs',\n",
       " 'getclasstree',\n",
       " 'getclosurevars',\n",
       " 'getcomments',\n",
       " 'getcoroutinelocals',\n",
       " 'getcoroutinestate',\n",
       " 'getdoc',\n",
       " 'getfile',\n",
       " 'getframeinfo',\n",
       " 'getfullargspec',\n",
       " 'getgeneratorlocals',\n",
       " 'getgeneratorstate',\n",
       " 'getinnerframes',\n",
       " 'getlineno',\n",
       " 'getmembers',\n",
       " 'getmodule',\n",
       " 'getmodulename',\n",
       " 'getmro',\n",
       " 'getouterframes',\n",
       " 'getsource',\n",
       " 'getsourcefile',\n",
       " 'getsourcelines',\n",
       " 'importlib',\n",
       " 'indentsize',\n",
       " 'isabstract',\n",
       " 'isasyncgen',\n",
       " 'isasyncgenfunction',\n",
       " 'isawaitable',\n",
       " 'isbuiltin',\n",
       " 'isclass',\n",
       " 'iscode',\n",
       " 'iscoroutine',\n",
       " 'iscoroutinefunction',\n",
       " 'isdatadescriptor',\n",
       " 'isframe',\n",
       " 'isfunction',\n",
       " 'isgenerator',\n",
       " 'isgeneratorfunction',\n",
       " 'isgetsetdescriptor',\n",
       " 'ismemberdescriptor',\n",
       " 'ismethod',\n",
       " 'ismethoddescriptor',\n",
       " 'ismodule',\n",
       " 'isroutine',\n",
       " 'istraceback',\n",
       " 'itertools',\n",
       " 'k',\n",
       " 'linecache',\n",
       " 'mod_dict',\n",
       " 'modulesbyfile',\n",
       " 'namedtuple',\n",
       " 'os',\n",
       " 're',\n",
       " 'signature',\n",
       " 'stack',\n",
       " 'sys',\n",
       " 'token',\n",
       " 'tokenize',\n",
       " 'trace',\n",
       " 'types',\n",
       " 'unwrap',\n",
       " 'v',\n",
       " 'walktree',\n",
       " 'warnings']"
      ]
     },
     "execution_count": 2,
     "metadata": {},
     "output_type": "execute_result"
    }
   ],
   "source": [
    "dir(inspect)"
   ]
  },
  {
   "cell_type": "code",
   "execution_count": 5,
   "metadata": {},
   "outputs": [
    {
     "data": {
      "text/plain": [
       "(['a = func(lambda : 42)\\n'], 6)"
      ]
     },
     "execution_count": 5,
     "metadata": {},
     "output_type": "execute_result"
    }
   ],
   "source": [
    "inspect.getsourcelines(a)"
   ]
  },
  {
   "cell_type": "code",
   "execution_count": 7,
   "metadata": {},
   "outputs": [
    {
     "data": {
      "text/plain": [
       "['Bytecode',\n",
       " 'COMPILER_FLAG_NAMES',\n",
       " 'EXTENDED_ARG',\n",
       " 'FORMAT_VALUE',\n",
       " 'HAVE_ARGUMENT',\n",
       " 'Instruction',\n",
       " '_Instruction',\n",
       " '__all__',\n",
       " '__builtins__',\n",
       " '__cached__',\n",
       " '__doc__',\n",
       " '__file__',\n",
       " '__loader__',\n",
       " '__name__',\n",
       " '__package__',\n",
       " '__spec__',\n",
       " '_disassemble_bytes',\n",
       " '_disassemble_str',\n",
       " '_format_code_info',\n",
       " '_get_code_object',\n",
       " '_get_const_info',\n",
       " '_get_instructions_bytes',\n",
       " '_get_name_info',\n",
       " '_have_code',\n",
       " '_test',\n",
       " '_try_compile',\n",
       " '_unpack_opargs',\n",
       " 'cmp_op',\n",
       " 'code_info',\n",
       " 'collections',\n",
       " 'dis',\n",
       " 'disassemble',\n",
       " 'disco',\n",
       " 'distb',\n",
       " 'findlabels',\n",
       " 'findlinestarts',\n",
       " 'get_instructions',\n",
       " 'hascompare',\n",
       " 'hasconst',\n",
       " 'hasfree',\n",
       " 'hasjabs',\n",
       " 'hasjrel',\n",
       " 'haslocal',\n",
       " 'hasname',\n",
       " 'hasnargs',\n",
       " 'io',\n",
       " 'opmap',\n",
       " 'opname',\n",
       " 'pretty_flags',\n",
       " 'show_code',\n",
       " 'stack_effect',\n",
       " 'sys',\n",
       " 'types']"
      ]
     },
     "execution_count": 7,
     "metadata": {},
     "output_type": "execute_result"
    }
   ],
   "source": [
    "import dis\n",
    "dir(dis)"
   ]
  },
  {
   "cell_type": "code",
   "execution_count": 8,
   "metadata": {},
   "outputs": [
    {
     "data": {
      "text/plain": [
       "<code object <lambda> at 0x000002E46171BB70, file \"<ipython-input-1-f42620b82bdf>\", line 6>"
      ]
     },
     "execution_count": 8,
     "metadata": {},
     "output_type": "execute_result"
    }
   ],
   "source": [
    "getattr(a, '__code__')"
   ]
  },
  {
   "cell_type": "code",
   "execution_count": 9,
   "metadata": {},
   "outputs": [
    {
     "data": {
      "text/plain": [
       "['__class__',\n",
       " '__delattr__',\n",
       " '__dir__',\n",
       " '__doc__',\n",
       " '__eq__',\n",
       " '__format__',\n",
       " '__ge__',\n",
       " '__getattribute__',\n",
       " '__gt__',\n",
       " '__hash__',\n",
       " '__init__',\n",
       " '__init_subclass__',\n",
       " '__le__',\n",
       " '__lt__',\n",
       " '__ne__',\n",
       " '__new__',\n",
       " '__reduce__',\n",
       " '__reduce_ex__',\n",
       " '__repr__',\n",
       " '__setattr__',\n",
       " '__sizeof__',\n",
       " '__str__',\n",
       " '__subclasshook__',\n",
       " 'co_argcount',\n",
       " 'co_cellvars',\n",
       " 'co_code',\n",
       " 'co_consts',\n",
       " 'co_filename',\n",
       " 'co_firstlineno',\n",
       " 'co_flags',\n",
       " 'co_freevars',\n",
       " 'co_kwonlyargcount',\n",
       " 'co_lnotab',\n",
       " 'co_name',\n",
       " 'co_names',\n",
       " 'co_nlocals',\n",
       " 'co_stacksize',\n",
       " 'co_varnames']"
      ]
     },
     "execution_count": 9,
     "metadata": {},
     "output_type": "execute_result"
    }
   ],
   "source": [
    "dir(getattr(a, '__code__'))"
   ]
  },
  {
   "cell_type": "code",
   "execution_count": 11,
   "metadata": {},
   "outputs": [
    {
     "data": {
      "text/plain": [
       "b'd\\x01S\\x00'"
      ]
     },
     "execution_count": 11,
     "metadata": {},
     "output_type": "execute_result"
    }
   ],
   "source": [
    "getattr(getattr(a, '__code__'), 'co_code')"
   ]
  },
  {
   "cell_type": "code",
   "execution_count": 1,
   "metadata": {},
   "outputs": [
    {
     "name": "stdout",
     "output_type": "stream",
     "text": [
      "  2           0 LOAD_FAST                1 (b)\n",
      "              2 POP_JUMP_IF_FALSE        8\n",
      "              4 LOAD_CONST               1 (1)\n",
      "              6 JUMP_FORWARD             2 (to 10)\n",
      "        >>    8 LOAD_CONST               2 (2)\n",
      "        >>   10 STORE_FAST               0 (a)\n",
      "             12 LOAD_CONST               0 (None)\n",
      "             14 RETURN_VALUE\n"
     ]
    }
   ],
   "source": [
    "def disasm_501(a,b):\n",
    "    a = 1 if b else 2\n",
    "import dis\n",
    "dis.dis(disasm_501)"
   ]
  },
  {
   "cell_type": "code",
   "execution_count": 3,
   "metadata": {},
   "outputs": [
    {
     "name": "stdout",
     "output_type": "stream",
     "text": [
      "  2           0 LOAD_FAST                1 (b)\n",
      "              2 POP_JUMP_IF_FALSE        8\n",
      "              4 LOAD_CONST               1 (1)\n",
      "              6 JUMP_FORWARD            10 (to 18)\n",
      "        >>    8 LOAD_FAST                0 (a)\n",
      "             10 POP_JUMP_IF_FALSE       16\n",
      "             12 LOAD_CONST               2 (2)\n",
      "             14 JUMP_FORWARD             2 (to 18)\n",
      "        >>   16 LOAD_CONST               3 (3)\n",
      "        >>   18 STORE_FAST               0 (a)\n",
      "             20 LOAD_CONST               0 (None)\n",
      "             22 RETURN_VALUE\n",
      "The history saving thread hit an unexpected error (OperationalError('database is locked',)).History will not be written to the database.\n"
     ]
    }
   ],
   "source": [
    "def disasm_502(a,b):\n",
    "    a = 1 if b else 2 if a else 3\n",
    "import dis\n",
    "dis.dis(disasm_502)    "
   ]
  },
  {
   "cell_type": "code",
   "execution_count": 8,
   "metadata": {},
   "outputs": [],
   "source": [
    "def f(a):\n",
    "    return a;\n",
    "\n",
    "def g(a):\n",
    "    for i in range(100):\n",
    "        k += f(f(f(f(f(f(f(f(f(f(f(f(f(f(f(f(f(f(f(f(f(f(f(f(f(f(f(f(f(f(f(f(f(f(f(f(f(f(f(f(f(f(f(f(f(f(f(f(f(f(f(f(f(f(f(f(f(f(f(f(f(f(f(f(f(f(f(f())))))))))))))))))))))))))))))))))))))))))))))))))))))))))))))))))))\n"
   ]
  },
  {
   "cell_type": "code",
   "execution_count": 9,
   "metadata": {},
   "outputs": [
    {
     "name": "stdout",
     "output_type": "stream",
     "text": [
      "  5           0 EXTENDED_ARG             1\n",
      "              2 SETUP_LOOP             296 (to 300)\n",
      "              4 LOAD_GLOBAL              0 (range)\n",
      "              6 LOAD_CONST               1 (100)\n",
      "              8 CALL_FUNCTION            1\n",
      "             10 GET_ITER\n",
      "        >>   12 EXTENDED_ARG             1\n",
      "             14 FOR_ITER               282 (to 298)\n",
      "             16 STORE_FAST               1 (i)\n",
      "\n",
      "  6          18 LOAD_FAST                2 (k)\n",
      "             20 LOAD_GLOBAL              1 (f)\n",
      "             22 LOAD_GLOBAL              1 (f)\n",
      "             24 LOAD_GLOBAL              1 (f)\n",
      "             26 LOAD_GLOBAL              1 (f)\n",
      "             28 LOAD_GLOBAL              1 (f)\n",
      "             30 LOAD_GLOBAL              1 (f)\n",
      "             32 LOAD_GLOBAL              1 (f)\n",
      "             34 LOAD_GLOBAL              1 (f)\n",
      "             36 LOAD_GLOBAL              1 (f)\n",
      "             38 LOAD_GLOBAL              1 (f)\n",
      "             40 LOAD_GLOBAL              1 (f)\n",
      "             42 LOAD_GLOBAL              1 (f)\n",
      "             44 LOAD_GLOBAL              1 (f)\n",
      "             46 LOAD_GLOBAL              1 (f)\n",
      "             48 LOAD_GLOBAL              1 (f)\n",
      "             50 LOAD_GLOBAL              1 (f)\n",
      "             52 LOAD_GLOBAL              1 (f)\n",
      "             54 LOAD_GLOBAL              1 (f)\n",
      "             56 LOAD_GLOBAL              1 (f)\n",
      "             58 LOAD_GLOBAL              1 (f)\n",
      "             60 LOAD_GLOBAL              1 (f)\n",
      "             62 LOAD_GLOBAL              1 (f)\n",
      "             64 LOAD_GLOBAL              1 (f)\n",
      "             66 LOAD_GLOBAL              1 (f)\n",
      "             68 LOAD_GLOBAL              1 (f)\n",
      "             70 LOAD_GLOBAL              1 (f)\n",
      "             72 LOAD_GLOBAL              1 (f)\n",
      "             74 LOAD_GLOBAL              1 (f)\n",
      "             76 LOAD_GLOBAL              1 (f)\n",
      "             78 LOAD_GLOBAL              1 (f)\n",
      "             80 LOAD_GLOBAL              1 (f)\n",
      "             82 LOAD_GLOBAL              1 (f)\n",
      "             84 LOAD_GLOBAL              1 (f)\n",
      "             86 LOAD_GLOBAL              1 (f)\n",
      "             88 LOAD_GLOBAL              1 (f)\n",
      "             90 LOAD_GLOBAL              1 (f)\n",
      "             92 LOAD_GLOBAL              1 (f)\n",
      "             94 LOAD_GLOBAL              1 (f)\n",
      "             96 LOAD_GLOBAL              1 (f)\n",
      "             98 LOAD_GLOBAL              1 (f)\n",
      "            100 LOAD_GLOBAL              1 (f)\n",
      "            102 LOAD_GLOBAL              1 (f)\n",
      "            104 LOAD_GLOBAL              1 (f)\n",
      "            106 LOAD_GLOBAL              1 (f)\n",
      "            108 LOAD_GLOBAL              1 (f)\n",
      "            110 LOAD_GLOBAL              1 (f)\n",
      "            112 LOAD_GLOBAL              1 (f)\n",
      "            114 LOAD_GLOBAL              1 (f)\n",
      "            116 LOAD_GLOBAL              1 (f)\n",
      "            118 LOAD_GLOBAL              1 (f)\n",
      "            120 LOAD_GLOBAL              1 (f)\n",
      "            122 LOAD_GLOBAL              1 (f)\n",
      "            124 LOAD_GLOBAL              1 (f)\n",
      "            126 LOAD_GLOBAL              1 (f)\n",
      "            128 LOAD_GLOBAL              1 (f)\n",
      "            130 LOAD_GLOBAL              1 (f)\n",
      "            132 LOAD_GLOBAL              1 (f)\n",
      "            134 LOAD_GLOBAL              1 (f)\n",
      "            136 LOAD_GLOBAL              1 (f)\n",
      "            138 LOAD_GLOBAL              1 (f)\n",
      "            140 LOAD_GLOBAL              1 (f)\n",
      "            142 LOAD_GLOBAL              1 (f)\n",
      "            144 LOAD_GLOBAL              1 (f)\n",
      "            146 LOAD_GLOBAL              1 (f)\n",
      "            148 LOAD_GLOBAL              1 (f)\n",
      "            150 LOAD_GLOBAL              1 (f)\n",
      "            152 LOAD_GLOBAL              1 (f)\n",
      "            154 LOAD_GLOBAL              1 (f)\n",
      "            156 CALL_FUNCTION            0\n",
      "            158 CALL_FUNCTION            1\n",
      "            160 CALL_FUNCTION            1\n",
      "            162 CALL_FUNCTION            1\n",
      "            164 CALL_FUNCTION            1\n",
      "            166 CALL_FUNCTION            1\n",
      "            168 CALL_FUNCTION            1\n",
      "            170 CALL_FUNCTION            1\n",
      "            172 CALL_FUNCTION            1\n",
      "            174 CALL_FUNCTION            1\n",
      "            176 CALL_FUNCTION            1\n",
      "            178 CALL_FUNCTION            1\n",
      "            180 CALL_FUNCTION            1\n",
      "            182 CALL_FUNCTION            1\n",
      "            184 CALL_FUNCTION            1\n",
      "            186 CALL_FUNCTION            1\n",
      "            188 CALL_FUNCTION            1\n",
      "            190 CALL_FUNCTION            1\n",
      "            192 CALL_FUNCTION            1\n",
      "            194 CALL_FUNCTION            1\n",
      "            196 CALL_FUNCTION            1\n",
      "            198 CALL_FUNCTION            1\n",
      "            200 CALL_FUNCTION            1\n",
      "            202 CALL_FUNCTION            1\n",
      "            204 CALL_FUNCTION            1\n",
      "            206 CALL_FUNCTION            1\n",
      "            208 CALL_FUNCTION            1\n",
      "            210 CALL_FUNCTION            1\n",
      "            212 CALL_FUNCTION            1\n",
      "            214 CALL_FUNCTION            1\n",
      "            216 CALL_FUNCTION            1\n",
      "            218 CALL_FUNCTION            1\n",
      "            220 CALL_FUNCTION            1\n",
      "            222 CALL_FUNCTION            1\n",
      "            224 CALL_FUNCTION            1\n",
      "            226 CALL_FUNCTION            1\n",
      "            228 CALL_FUNCTION            1\n",
      "            230 CALL_FUNCTION            1\n",
      "            232 CALL_FUNCTION            1\n",
      "            234 CALL_FUNCTION            1\n",
      "            236 CALL_FUNCTION            1\n",
      "            238 CALL_FUNCTION            1\n",
      "            240 CALL_FUNCTION            1\n",
      "            242 CALL_FUNCTION            1\n",
      "            244 CALL_FUNCTION            1\n",
      "            246 CALL_FUNCTION            1\n",
      "            248 CALL_FUNCTION            1\n",
      "            250 CALL_FUNCTION            1\n",
      "            252 CALL_FUNCTION            1\n",
      "            254 CALL_FUNCTION            1\n",
      "            256 CALL_FUNCTION            1\n",
      "            258 CALL_FUNCTION            1\n",
      "            260 CALL_FUNCTION            1\n",
      "            262 CALL_FUNCTION            1\n",
      "            264 CALL_FUNCTION            1\n",
      "            266 CALL_FUNCTION            1\n",
      "            268 CALL_FUNCTION            1\n",
      "            270 CALL_FUNCTION            1\n",
      "            272 CALL_FUNCTION            1\n",
      "            274 CALL_FUNCTION            1\n",
      "            276 CALL_FUNCTION            1\n",
      "            278 CALL_FUNCTION            1\n",
      "            280 CALL_FUNCTION            1\n",
      "            282 CALL_FUNCTION            1\n",
      "            284 CALL_FUNCTION            1\n",
      "            286 CALL_FUNCTION            1\n",
      "            288 CALL_FUNCTION            1\n",
      "            290 CALL_FUNCTION            1\n",
      "            292 INPLACE_ADD\n",
      "            294 STORE_FAST               2 (k)\n",
      "            296 JUMP_ABSOLUTE           12\n",
      "        >>  298 POP_BLOCK\n",
      "        >>  300 LOAD_CONST               0 (None)\n",
      "            302 RETURN_VALUE\n"
     ]
    }
   ],
   "source": [
    "import dis\n",
    "dis.dis(g)"
   ]
  },
  {
   "cell_type": "code",
   "execution_count": 20,
   "metadata": {},
   "outputs": [
    {
     "data": {
      "text/plain": [
       "304"
      ]
     },
     "execution_count": 20,
     "metadata": {},
     "output_type": "execute_result"
    }
   ],
   "source": [
    "getattr(g,'__code__').co_code.__len__()"
   ]
  },
  {
   "cell_type": "code",
   "execution_count": 1,
   "metadata": {},
   "outputs": [
    {
     "data": {
      "text/plain": [
       "['__annotations__',\n",
       " '__call__',\n",
       " '__class__',\n",
       " '__closure__',\n",
       " '__code__',\n",
       " '__defaults__',\n",
       " '__delattr__',\n",
       " '__dict__',\n",
       " '__dir__',\n",
       " '__doc__',\n",
       " '__eq__',\n",
       " '__format__',\n",
       " '__ge__',\n",
       " '__get__',\n",
       " '__getattribute__',\n",
       " '__globals__',\n",
       " '__gt__',\n",
       " '__hash__',\n",
       " '__init__',\n",
       " '__init_subclass__',\n",
       " '__kwdefaults__',\n",
       " '__le__',\n",
       " '__lt__',\n",
       " '__module__',\n",
       " '__name__',\n",
       " '__ne__',\n",
       " '__new__',\n",
       " '__qualname__',\n",
       " '__reduce__',\n",
       " '__reduce_ex__',\n",
       " '__repr__',\n",
       " '__setattr__',\n",
       " '__sizeof__',\n",
       " '__str__',\n",
       " '__subclasshook__']"
      ]
     },
     "execution_count": 1,
     "metadata": {},
     "output_type": "execute_result"
    }
   ],
   "source": [
    "z = lambda : 42\n",
    "dir(z)"
   ]
  },
  {
   "cell_type": "code",
   "execution_count": 2,
   "metadata": {},
   "outputs": [
    {
     "name": "stdout",
     "output_type": "stream",
     "text": [
      "  1           0 LOAD_CONST               1 (42)\n",
      "              2 RETURN_VALUE\n"
     ]
    }
   ],
   "source": [
    "import dis\n",
    "dis.dis(getattr(z,'__code__'))"
   ]
  },
  {
   "cell_type": "code",
   "execution_count": 1,
   "metadata": {},
   "outputs": [
    {
     "data": {
      "text/plain": [
       "42"
      ]
     },
     "execution_count": 1,
     "metadata": {},
     "output_type": "execute_result"
    }
   ],
   "source": [
    "2+40"
   ]
  },
  {
   "cell_type": "code",
   "execution_count": 1,
   "metadata": {},
   "outputs": [
    {
     "name": "stdout",
     "output_type": "stream",
     "text": [
      "  2           0 LOAD_FAST                1 (b)\n",
      "              2 POP_JUMP_IF_FALSE        8\n",
      "              4 LOAD_CONST               1 (1)\n",
      "              6 JUMP_FORWARD             2 (to 10)\n",
      "        >>    8 LOAD_CONST               2 (2)\n",
      "        >>   10 STORE_FAST               0 (a)\n",
      "             12 LOAD_CONST               0 (None)\n",
      "             14 RETURN_VALUE\n"
     ]
    }
   ],
   "source": [
    "def disasm_501(a,b):\n",
    "    a = 1 if b else 2\n",
    "    \n",
    "import dis\n",
    "dis.dis(disasm_501)"
   ]
  },
  {
   "cell_type": "code",
   "execution_count": 2,
   "metadata": {},
   "outputs": [
    {
     "name": "stdout",
     "output_type": "stream",
     "text": [
      "  2           0 LOAD_FAST                1 (b)\n",
      "              2 POP_JUMP_IF_FALSE        8\n",
      "              4 LOAD_CONST               1 (1)\n",
      "              6 JUMP_FORWARD            10 (to 18)\n",
      "        >>    8 LOAD_FAST                0 (a)\n",
      "             10 POP_JUMP_IF_FALSE       16\n",
      "             12 LOAD_CONST               2 (2)\n",
      "             14 JUMP_FORWARD             2 (to 18)\n",
      "        >>   16 LOAD_CONST               3 (3)\n",
      "        >>   18 STORE_FAST               0 (a)\n",
      "             20 LOAD_CONST               0 (None)\n",
      "             22 RETURN_VALUE\n"
     ]
    }
   ],
   "source": [
    "def disasm_502(a,b):\n",
    "    a = 1 if b else 2 if a else 3\n",
    "\n",
    "import dis\n",
    "dis.dis(disasm_502)"
   ]
  },
  {
   "cell_type": "code",
   "execution_count": 1,
   "metadata": {},
   "outputs": [
    {
     "name": "stdout",
     "output_type": "stream",
     "text": [
      "  2           0 LOAD_FAST                1 (b)\n",
      "              2 POP_JUMP_IF_FALSE       10\n",
      "\n",
      "  3           4 LOAD_CONST               1 (1)\n",
      "              6 STORE_FAST               0 (a)\n",
      "              8 JUMP_FORWARD             4 (to 14)\n",
      "\n",
      "  5     >>   10 LOAD_CONST               2 (2)\n",
      "             12 STORE_FAST               0 (a)\n",
      "        >>   14 LOAD_CONST               0 (None)\n",
      "             16 RETURN_VALUE\n"
     ]
    }
   ],
   "source": [
    "def disasm_503(a,b):\n",
    "    if b:\n",
    "        a = 1\n",
    "    else:\n",
    "        a = 2\n",
    "        \n",
    "import dis\n",
    "dis.dis(disasm_503)"
   ]
  },
  {
   "cell_type": "code",
   "execution_count": 13,
   "metadata": {},
   "outputs": [
    {
     "name": "stdout",
     "output_type": "stream",
     "text": [
      "  2           0 SETUP_LOOP              24 (to 26)\n",
      "              2 LOAD_GLOBAL              0 (range)\n",
      "              4 LOAD_CONST               1 (1)\n",
      "              6 CALL_FUNCTION            1\n",
      "              8 GET_ITER\n",
      "        >>   10 FOR_ITER                12 (to 24)\n",
      "             12 STORE_FAST               0 (i)\n",
      "\n",
      "  3          14 LOAD_FAST                1 (x)\n",
      "             16 LOAD_FAST                0 (i)\n",
      "             18 BINARY_ADD\n",
      "             20 STORE_FAST               1 (x)\n",
      "             22 JUMP_ABSOLUTE           10\n",
      "        >>   24 POP_BLOCK\n",
      "        >>   26 LOAD_CONST               0 (None)\n",
      "             28 RETURN_VALUE\n"
     ]
    }
   ],
   "source": [
    "def disasm_513():\n",
    "    for i in range(1):\n",
    "        x = x+i\n",
    "        \n",
    "getattr(getattr(disasm_513,'__code__'), 'co_names')\n",
    "\n",
    "import dis\n",
    "dis.dis(disasm_513)\n"
   ]
  },
  {
   "cell_type": "code",
   "execution_count": 10,
   "metadata": {},
   "outputs": [
    {
     "name": "stdout",
     "output_type": "stream",
     "text": [
      "  2           0 LOAD_GLOBAL              0 (print)\n",
      "              2 LOAD_CONST               1 (42)\n",
      "              4 CALL_FUNCTION            1\n",
      "              6 POP_TOP\n",
      "              8 LOAD_CONST               0 (None)\n",
      "             10 RETURN_VALUE\n"
     ]
    }
   ],
   "source": [
    "def disasm_514():\n",
    "    print(42)\n",
    "        \n",
    "getattr(getattr(disasm_514,'__code__'), 'co_names')\n",
    "\n",
    "import dis\n",
    "dis.dis(disasm_514)"
   ]
  },
  {
   "cell_type": "code",
   "execution_count": 34,
   "metadata": {},
   "outputs": [
    {
     "name": "stdout",
     "output_type": "stream",
     "text": [
      "  2           0 SETUP_LOOP              34 (to 36)\n",
      "              2 LOAD_GLOBAL              0 (range)\n",
      "              4 LOAD_CONST               1 (1)\n",
      "              6 CALL_FUNCTION            1\n",
      "              8 GET_ITER\n",
      "        >>   10 FOR_ITER                22 (to 34)\n",
      "             12 STORE_FAST               0 (i)\n",
      "\n",
      "  3          14 LOAD_FAST                1 (x)\n",
      "             16 LOAD_FAST                0 (i)\n",
      "             18 BINARY_ADD\n",
      "             20 STORE_FAST               1 (x)\n",
      "\n",
      "  4          22 LOAD_FAST                1 (x)\n",
      "             24 LOAD_CONST               2 (3)\n",
      "             26 COMPARE_OP               4 (>)\n",
      "             28 POP_JUMP_IF_FALSE       10\n",
      "\n",
      "  5          30 JUMP_ABSOLUTE           10\n",
      "             32 JUMP_ABSOLUTE           10\n",
      "        >>   34 POP_BLOCK\n",
      "        >>   36 LOAD_CONST               0 (None)\n",
      "             38 RETURN_VALUE\n"
     ]
    }
   ],
   "source": [
    "def disasm_515():\n",
    "    for i in range(1):\n",
    "        x = x+i\n",
    "        if (x > 3):\n",
    "            continue\n",
    "        # x = x - 1\n",
    "import dis\n",
    "dis.dis(disasm_515)            "
   ]
  },
  {
   "cell_type": "code",
   "execution_count": 18,
   "metadata": {},
   "outputs": [
    {
     "name": "stdout",
     "output_type": "stream",
     "text": [
      "  2           0 LOAD_CONST               1 (0)\n",
      "              2 STORE_FAST               2 (x)\n",
      "\n",
      "  3           4 SETUP_LOOP              30 (to 36)\n",
      "        >>    6 LOAD_FAST                2 (x)\n",
      "              8 LOAD_FAST                0 (a)\n",
      "             10 COMPARE_OP               0 (<)\n",
      "             12 POP_JUMP_IF_FALSE       34\n",
      "\n",
      "  4          14 LOAD_FAST                2 (x)\n",
      "             16 LOAD_CONST               2 (1)\n",
      "             18 BINARY_ADD\n",
      "             20 STORE_FAST               2 (x)\n",
      "\n",
      "  5          22 LOAD_FAST                2 (x)\n",
      "             24 LOAD_CONST               3 (3)\n",
      "             26 COMPARE_OP               4 (>)\n",
      "             28 POP_JUMP_IF_FALSE        6\n",
      "\n",
      "  6          30 JUMP_ABSOLUTE            6\n",
      "             32 JUMP_ABSOLUTE            6\n",
      "        >>   34 POP_BLOCK\n",
      "\n",
      "  7     >>   36 LOAD_FAST                2 (x)\n",
      "             38 LOAD_CONST               2 (1)\n",
      "             40 BINARY_SUBTRACT\n",
      "             42 STORE_FAST               2 (x)\n",
      "             44 LOAD_CONST               0 (None)\n",
      "             46 RETURN_VALUE\n"
     ]
    }
   ],
   "source": [
    "def disasm_511(a,b):\n",
    "    x = 0\n",
    "    while (x < a):\n",
    "        x = x + 1\n",
    "        if (x > 3):\n",
    "            continue\n",
    "    x = x - 1\n",
    "        \n",
    "import dis\n",
    "dis.dis(disasm_511)"
   ]
  },
  {
   "cell_type": "code",
   "execution_count": 28,
   "metadata": {},
   "outputs": [
    {
     "name": "stdout",
     "output_type": "stream",
     "text": [
      "  2           0 LOAD_FAST                0 (a)\n",
      "              2 POP_JUMP_IF_FALSE       26\n",
      "\n",
      "  3           4 LOAD_FAST                1 (b)\n",
      "              6 POP_JUMP_IF_FALSE       18\n",
      "\n",
      "  4           8 LOAD_GLOBAL              0 (print)\n",
      "             10 LOAD_CONST               1 (42)\n",
      "             12 CALL_FUNCTION            1\n",
      "             14 POP_TOP\n",
      "             16 JUMP_FORWARD             8 (to 26)\n",
      "\n",
      "  6     >>   18 LOAD_GLOBAL              0 (print)\n",
      "             20 LOAD_CONST               2 (33)\n",
      "             22 CALL_FUNCTION            1\n",
      "             24 POP_TOP\n",
      "\n",
      "  7     >>   26 LOAD_GLOBAL              0 (print)\n",
      "             28 LOAD_CONST               3 (34)\n",
      "             30 CALL_FUNCTION            1\n",
      "             32 POP_TOP\n",
      "             34 LOAD_CONST               0 (None)\n",
      "             36 RETURN_VALUE\n"
     ]
    }
   ],
   "source": [
    "def disasm_512(a,b):\n",
    "    if (a):\n",
    "        if (b):\n",
    "            print(42)\n",
    "        else:\n",
    "            print(33)\n",
    "    print(34)\n",
    "    \n",
    "import dis\n",
    "dis.dis(disasm_512)"
   ]
  },
  {
   "cell_type": "code",
   "execution_count": 35,
   "metadata": {},
   "outputs": [
    {
     "name": "stdout",
     "output_type": "stream",
     "text": [
      "  2           0 LOAD_FAST                1 (b)\n",
      "              2 POP_JUMP_IF_FALSE        8\n",
      "              4 LOAD_CONST               1 (1)\n",
      "              6 JUMP_FORWARD             2 (to 10)\n",
      "        >>    8 LOAD_CONST               2 (2)\n",
      "        >>   10 STORE_FAST               0 (a)\n",
      "             12 LOAD_CONST               0 (None)\n",
      "             14 RETURN_VALUE\n"
     ]
    }
   ],
   "source": [
    "def disasm_501(a,b):\n",
    "    a = 1 if b else 2\n",
    "\n",
    "import dis\n",
    "dis.dis(disasm_501)    "
   ]
  },
  {
   "cell_type": "code",
   "execution_count": 36,
   "metadata": {},
   "outputs": [
    {
     "name": "stdout",
     "output_type": "stream",
     "text": [
      "  2           0 LOAD_FAST                0 (a)\n",
      "              2 POP_JUMP_IF_FALSE       20\n",
      "\n",
      "  3           4 LOAD_FAST                1 (b)\n",
      "              6 POP_JUMP_IF_FALSE       14\n",
      "\n",
      "  4           8 LOAD_CONST               1 (1)\n",
      "             10 STORE_FAST               2 (c)\n",
      "             12 JUMP_ABSOLUTE           34\n",
      "\n",
      "  6     >>   14 LOAD_CONST               2 (2)\n",
      "             16 STORE_FAST               2 (c)\n",
      "             18 JUMP_FORWARD            14 (to 34)\n",
      "\n",
      "  8     >>   20 LOAD_FAST                1 (b)\n",
      "             22 POP_JUMP_IF_FALSE       30\n",
      "\n",
      "  9          24 LOAD_CONST               3 (3)\n",
      "             26 STORE_FAST               2 (c)\n",
      "             28 JUMP_FORWARD             4 (to 34)\n",
      "\n",
      " 11     >>   30 LOAD_CONST               4 (4)\n",
      "             32 STORE_FAST               2 (c)\n",
      "        >>   34 LOAD_CONST               0 (None)\n",
      "             36 RETURN_VALUE\n"
     ]
    }
   ],
   "source": [
    "def disasm_505(a,b,c):\n",
    "    if a:\n",
    "        if b:\n",
    "            c = 1\n",
    "        else:\n",
    "            c = 2\n",
    "    else:\n",
    "        if b:\n",
    "            c = 3\n",
    "        else:\n",
    "            c = 4\n",
    "        \n",
    "import dis\n",
    "dis.dis(disasm_505)"
   ]
  },
  {
   "cell_type": "code",
   "execution_count": 2,
   "metadata": {},
   "outputs": [
    {
     "name": "stdout",
     "output_type": "stream",
     "text": [
      "  2           0 LOAD_FAST                0 (a)\n",
      "              2 POP_JUMP_IF_FALSE       12\n",
      "\n",
      "  3           4 LOAD_FAST                1 (b)\n",
      "              6 POP_JUMP_IF_FALSE       12\n",
      "\n",
      "  4           8 LOAD_CONST               1 (1)\n",
      "             10 STORE_FAST               2 (c)\n",
      "        >>   12 LOAD_CONST               0 (None)\n",
      "             14 RETURN_VALUE\n"
     ]
    }
   ],
   "source": [
    "def disasm_505(a,b,c):\n",
    "    if a:\n",
    "        if b:\n",
    "            c = 1\n",
    "        \n",
    "import dis\n",
    "dis.dis(disasm_505)"
   ]
  },
  {
   "cell_type": "code",
   "execution_count": 3,
   "metadata": {},
   "outputs": [
    {
     "name": "stdout",
     "output_type": "stream",
     "text": [
      "  2           0 LOAD_FAST                1 (b)\n",
      "              2 POP_JUMP_IF_FALSE       10\n",
      "\n",
      "  3           4 LOAD_CONST               1 (1)\n",
      "              6 STORE_FAST               0 (a)\n",
      "              8 JUMP_FORWARD             4 (to 14)\n",
      "\n",
      "  5     >>   10 LOAD_CONST               2 (2)\n",
      "             12 STORE_FAST               0 (a)\n",
      "        >>   14 LOAD_CONST               0 (None)\n",
      "             16 RETURN_VALUE\n"
     ]
    }
   ],
   "source": [
    "def disasm_503(a,b):\n",
    "    if b:\n",
    "        a = 1\n",
    "    else:\n",
    "        a = 2\n",
    "        \n",
    "import dis\n",
    "dis.dis(disasm_503)"
   ]
  },
  {
   "cell_type": "code",
   "execution_count": 4,
   "metadata": {},
   "outputs": [
    {
     "name": "stdout",
     "output_type": "stream",
     "text": [
      "  2           0 LOAD_CONST               1 (0)\n",
      "              2 STORE_FAST               2 (x)\n",
      "\n",
      "  3           4 SETUP_LOOP              20 (to 26)\n",
      "        >>    6 LOAD_FAST                2 (x)\n",
      "              8 LOAD_FAST                0 (a)\n",
      "             10 COMPARE_OP               0 (<)\n",
      "             12 POP_JUMP_IF_FALSE       24\n",
      "\n",
      "  4          14 LOAD_FAST                2 (x)\n",
      "             16 LOAD_CONST               2 (1)\n",
      "             18 BINARY_ADD\n",
      "             20 STORE_FAST               2 (x)\n",
      "             22 JUMP_ABSOLUTE            6\n",
      "        >>   24 POP_BLOCK\n",
      "        >>   26 LOAD_CONST               0 (None)\n",
      "             28 RETURN_VALUE\n"
     ]
    }
   ],
   "source": [
    "def disasm_510(a,b):\n",
    "    x = 0\n",
    "    while (x < a):\n",
    "        x = x + 1\n",
    "import dis\n",
    "dis.dis(disasm_510)"
   ]
  },
  {
   "cell_type": "code",
   "execution_count": 5,
   "metadata": {},
   "outputs": [
    {
     "name": "stdout",
     "output_type": "stream",
     "text": [
      "  2           0 LOAD_CONST               1 (0)\n",
      "              2 STORE_FAST               2 (x)\n",
      "\n",
      "  3           4 SETUP_LOOP              22 (to 28)\n",
      "        >>    6 LOAD_FAST                2 (x)\n",
      "              8 LOAD_FAST                0 (a)\n",
      "             10 COMPARE_OP               0 (<)\n",
      "             12 POP_JUMP_IF_FALSE       26\n",
      "\n",
      "  4          14 LOAD_FAST                2 (x)\n",
      "             16 LOAD_CONST               2 (1)\n",
      "             18 BINARY_ADD\n",
      "             20 STORE_FAST               2 (x)\n",
      "\n",
      "  5          22 BREAK_LOOP\n",
      "             24 JUMP_ABSOLUTE            6\n",
      "        >>   26 POP_BLOCK\n",
      "\n",
      "  6     >>   28 LOAD_FAST                2 (x)\n",
      "             30 LOAD_CONST               2 (1)\n",
      "             32 BINARY_SUBTRACT\n",
      "             34 STORE_FAST               2 (x)\n",
      "             36 LOAD_CONST               0 (None)\n",
      "             38 RETURN_VALUE\n",
      "The history saving thread hit an unexpected error (OperationalError('database is locked',)).History will not be written to the database.\n"
     ]
    }
   ],
   "source": [
    "def disasm_512(a,b):\n",
    "    x = 0\n",
    "    while (x < a):\n",
    "        x = x + 1\n",
    "        break\n",
    "    x = x - 1\n",
    "        \n",
    "import dis\n",
    "dis.dis(disasm_512)"
   ]
  },
  {
   "cell_type": "code",
   "execution_count": 6,
   "metadata": {},
   "outputs": [
    {
     "name": "stdout",
     "output_type": "stream",
     "text": [
      "  2           0 SETUP_LOOP              34 (to 36)\n",
      "              2 LOAD_GLOBAL              0 (range)\n",
      "              4 LOAD_CONST               1 (1)\n",
      "              6 CALL_FUNCTION            1\n",
      "              8 GET_ITER\n",
      "        >>   10 FOR_ITER                22 (to 34)\n",
      "             12 STORE_FAST               0 (i)\n",
      "\n",
      "  3          14 LOAD_FAST                1 (x)\n",
      "             16 LOAD_FAST                0 (i)\n",
      "             18 BINARY_ADD\n",
      "             20 STORE_FAST               1 (x)\n",
      "\n",
      "  4          22 LOAD_FAST                1 (x)\n",
      "             24 LOAD_CONST               2 (3)\n",
      "             26 COMPARE_OP               4 (>)\n",
      "             28 POP_JUMP_IF_FALSE       10\n",
      "\n",
      "  5          30 JUMP_ABSOLUTE           10\n",
      "             32 JUMP_ABSOLUTE           10\n",
      "        >>   34 POP_BLOCK\n",
      "        >>   36 LOAD_CONST               0 (None)\n",
      "             38 RETURN_VALUE\n"
     ]
    }
   ],
   "source": [
    "def disasm_514():\n",
    "    for i in range(1):\n",
    "        x = x+i\n",
    "        if (x > 3):\n",
    "            continue\n",
    "\n",
    "import dis\n",
    "dis.dis(disasm_514)"
   ]
  },
  {
   "cell_type": "code",
   "execution_count": 7,
   "metadata": {},
   "outputs": [
    {
     "name": "stdout",
     "output_type": "stream",
     "text": [
      "  2           0 LOAD_FAST                0 (a)\n",
      "              2 JUMP_IF_FALSE_OR_POP     6\n",
      "              4 LOAD_FAST                1 (b)\n",
      "        >>    6 LOAD_FAST                2 (c)\n",
      "              8 LOAD_CONST               1 (0)\n",
      "             10 STORE_SUBSCR\n",
      "\n",
      "  3          12 LOAD_FAST                0 (a)\n",
      "             14 JUMP_IF_TRUE_OR_POP     18\n",
      "             16 LOAD_FAST                1 (b)\n",
      "        >>   18 LOAD_FAST                2 (c)\n",
      "             20 LOAD_CONST               2 (1)\n",
      "             22 STORE_SUBSCR\n",
      "\n",
      "  4          24 LOAD_FAST                1 (b)\n",
      "             26 UNARY_NOT\n",
      "             28 LOAD_FAST                2 (c)\n",
      "             30 LOAD_CONST               3 (2)\n",
      "             32 STORE_SUBSCR\n",
      "             34 LOAD_CONST               0 (None)\n",
      "             36 RETURN_VALUE\n"
     ]
    }
   ],
   "source": [
    "def compare_bool_values(a,b,c):\n",
    "    c[0] = a and b\n",
    "    c[1] = a or b\n",
    "    c[2] = not b\n",
    "    \n",
    "import dis\n",
    "dis.dis(compare_bool_values)"
   ]
  },
  {
   "cell_type": "code",
   "execution_count": 9,
   "metadata": {},
   "outputs": [
    {
     "name": "stdout",
     "output_type": "stream",
     "text": [
      "  2           0 LOAD_FAST                0 (a)\n",
      "              2 POP_JUMP_IF_FALSE        8\n",
      "              4 LOAD_FAST                1 (b)\n",
      "              6 JUMP_FORWARD             2 (to 10)\n",
      "        >>    8 LOAD_FAST                0 (a)\n",
      "        >>   10 LOAD_FAST                2 (c)\n",
      "             12 LOAD_CONST               1 (0)\n",
      "             14 STORE_SUBSCR\n",
      "             16 LOAD_CONST               0 (None)\n",
      "             18 RETURN_VALUE\n"
     ]
    }
   ],
   "source": [
    "def compare_bool_values(a,b,c):\n",
    "    c[0] = b if a else a\n",
    "    \n",
    "import dis\n",
    "dis.dis(compare_bool_values)"
   ]
  },
  {
   "cell_type": "code",
   "execution_count": 10,
   "metadata": {},
   "outputs": [
    {
     "name": "stdout",
     "output_type": "stream",
     "text": [
      "  2           0 LOAD_FAST                0 (a)\n",
      "              2 JUMP_IF_FALSE_OR_POP    10\n",
      "              4 LOAD_FAST                1 (b)\n",
      "              6 JUMP_IF_FALSE_OR_POP    10\n",
      "              8 LOAD_GLOBAL              0 (c)\n",
      "        >>   10 RETURN_VALUE\n"
     ]
    }
   ],
   "source": [
    "def disasm_218(a,b):\n",
    "    return a and b and c\n",
    "\n",
    "import dis\n",
    "dis.dis(disasm_218)"
   ]
  },
  {
   "cell_type": "code",
   "execution_count": 12,
   "metadata": {},
   "outputs": [
    {
     "name": "stdout",
     "output_type": "stream",
     "text": [
      "  2           0 LOAD_FAST                0 (a)\n",
      "              2 JUMP_IF_TRUE_OR_POP     10\n",
      "              4 LOAD_FAST                1 (b)\n",
      "              6 JUMP_IF_FALSE_OR_POP    10\n",
      "              8 LOAD_FAST                2 (c)\n",
      "        >>   10 RETURN_VALUE\n"
     ]
    }
   ],
   "source": [
    "def disasm_220(a,b, c):\n",
    "    return a or b and c\n",
    "import dis\n",
    "dis.dis(disasm_220)"
   ]
  },
  {
   "cell_type": "code",
   "execution_count": 13,
   "metadata": {},
   "outputs": [
    {
     "name": "stdout",
     "output_type": "stream",
     "text": [
      "  2           0 LOAD_FAST                0 (a)\n",
      "              2 LOAD_FAST                1 (b)\n",
      "              4 LOAD_CONST               1 (0)\n",
      "              6 BINARY_SUBSCR\n",
      "              8 COMPARE_OP               2 (==)\n",
      "             10 POP_JUMP_IF_TRUE        16\n",
      "             12 LOAD_GLOBAL              0 (AssertionError)\n",
      "             14 RAISE_VARARGS            1\n",
      "        >>   16 LOAD_CONST               0 (None)\n",
      "             18 RETURN_VALUE\n"
     ]
    }
   ],
   "source": [
    "def assert_001(a,b):\n",
    "    assert (a == b[0])\n",
    "\n",
    "import dis\n",
    "dis.dis(assert_001)"
   ]
  },
  {
   "cell_type": "code",
   "execution_count": 17,
   "metadata": {},
   "outputs": [
    {
     "name": "stdout",
     "output_type": "stream",
     "text": [
      "  2           0 LOAD_FAST                0 (a)\n",
      "              2 LOAD_FAST                1 (b)\n",
      "              4 LOAD_CONST               1 (0)\n",
      "              6 BINARY_SUBSCR\n",
      "              8 COMPARE_OP               2 (==)\n",
      "             10 POP_JUMP_IF_TRUE        20\n",
      "             12 LOAD_GLOBAL              0 (AssertionError)\n",
      "             14 LOAD_CONST               2 ('delta')\n",
      "             16 CALL_FUNCTION            1\n",
      "             18 RAISE_VARARGS            1\n",
      "        >>   20 LOAD_CONST               0 (None)\n",
      "             22 RETURN_VALUE\n"
     ]
    }
   ],
   "source": [
    "def assert_002(a,b):\n",
    "    assert (a == b[0]), 'delta'\n",
    "\n",
    "import dis\n",
    "dis.dis(assert_002)"
   ]
  },
  {
   "cell_type": "code",
   "execution_count": 18,
   "metadata": {},
   "outputs": [],
   "source": [
    "c = lambda : 42"
   ]
  },
  {
   "cell_type": "code",
   "execution_count": 19,
   "metadata": {},
   "outputs": [
    {
     "data": {
      "text/plain": [
       "['__annotations__',\n",
       " '__call__',\n",
       " '__class__',\n",
       " '__closure__',\n",
       " '__code__',\n",
       " '__defaults__',\n",
       " '__delattr__',\n",
       " '__dict__',\n",
       " '__dir__',\n",
       " '__doc__',\n",
       " '__eq__',\n",
       " '__format__',\n",
       " '__ge__',\n",
       " '__get__',\n",
       " '__getattribute__',\n",
       " '__globals__',\n",
       " '__gt__',\n",
       " '__hash__',\n",
       " '__init__',\n",
       " '__init_subclass__',\n",
       " '__kwdefaults__',\n",
       " '__le__',\n",
       " '__lt__',\n",
       " '__module__',\n",
       " '__name__',\n",
       " '__ne__',\n",
       " '__new__',\n",
       " '__qualname__',\n",
       " '__reduce__',\n",
       " '__reduce_ex__',\n",
       " '__repr__',\n",
       " '__setattr__',\n",
       " '__sizeof__',\n",
       " '__str__',\n",
       " '__subclasshook__']"
      ]
     },
     "execution_count": 19,
     "metadata": {},
     "output_type": "execute_result"
    }
   ],
   "source": [
    "dir(c)"
   ]
  },
  {
   "cell_type": "code",
   "execution_count": 20,
   "metadata": {},
   "outputs": [
    {
     "data": {
      "text/plain": [
       "['__class__',\n",
       " '__delattr__',\n",
       " '__dir__',\n",
       " '__doc__',\n",
       " '__eq__',\n",
       " '__format__',\n",
       " '__ge__',\n",
       " '__getattribute__',\n",
       " '__gt__',\n",
       " '__hash__',\n",
       " '__init__',\n",
       " '__init_subclass__',\n",
       " '__le__',\n",
       " '__lt__',\n",
       " '__ne__',\n",
       " '__new__',\n",
       " '__reduce__',\n",
       " '__reduce_ex__',\n",
       " '__repr__',\n",
       " '__setattr__',\n",
       " '__sizeof__',\n",
       " '__str__',\n",
       " '__subclasshook__',\n",
       " 'co_argcount',\n",
       " 'co_cellvars',\n",
       " 'co_code',\n",
       " 'co_consts',\n",
       " 'co_filename',\n",
       " 'co_firstlineno',\n",
       " 'co_flags',\n",
       " 'co_freevars',\n",
       " 'co_kwonlyargcount',\n",
       " 'co_lnotab',\n",
       " 'co_name',\n",
       " 'co_names',\n",
       " 'co_nlocals',\n",
       " 'co_stacksize',\n",
       " 'co_varnames']"
      ]
     },
     "execution_count": 20,
     "metadata": {},
     "output_type": "execute_result"
    }
   ],
   "source": [
    "dir(getattr(c, '__code__'))"
   ]
  },
  {
   "cell_type": "code",
   "execution_count": 21,
   "metadata": {},
   "outputs": [
    {
     "name": "stdout",
     "output_type": "stream",
     "text": [
      "  1           0 LOAD_CONST               1 (42)\n",
      "              2 RETURN_VALUE\n"
     ]
    }
   ],
   "source": [
    "import dis\n",
    "dis.dis(c)"
   ]
  },
  {
   "cell_type": "code",
   "execution_count": 22,
   "metadata": {},
   "outputs": [
    {
     "data": {
      "text/plain": [
       "function"
      ]
     },
     "execution_count": 22,
     "metadata": {},
     "output_type": "execute_result"
    }
   ],
   "source": [
    "type(c)"
   ]
  },
  {
   "cell_type": "code",
   "execution_count": 23,
   "metadata": {},
   "outputs": [],
   "source": [
    "maxiter = 256\n",
    "c = lambda : maxiter"
   ]
  },
  {
   "cell_type": "code",
   "execution_count": 24,
   "metadata": {},
   "outputs": [
    {
     "data": {
      "text/plain": [
       "function"
      ]
     },
     "execution_count": 24,
     "metadata": {},
     "output_type": "execute_result"
    }
   ],
   "source": [
    "type(c)"
   ]
  },
  {
   "cell_type": "code",
   "execution_count": 25,
   "metadata": {},
   "outputs": [
    {
     "name": "stdout",
     "output_type": "stream",
     "text": [
      "  2           0 LOAD_GLOBAL              0 (maxiter)\n",
      "              2 RETURN_VALUE\n"
     ]
    }
   ],
   "source": [
    "import dis\n",
    "dis.dis(c)"
   ]
  },
  {
   "cell_type": "code",
   "execution_count": 35,
   "metadata": {},
   "outputs": [
    {
     "name": "stdout",
     "output_type": "stream",
     "text": [
      "  2           0 LOAD_DEREF               0 (x)\n",
      "              2 LOAD_DEREF               1 (y)\n",
      "              4 BINARY_ADD\n",
      "              6 RETURN_VALUE\n"
     ]
    }
   ],
   "source": [
    "def func(x,y):\n",
    "    z = lambda a,b : x+y\n",
    "    return z\n",
    "\n",
    "w = func(1,2)\n",
    "import dis\n",
    "dis.dis(w)"
   ]
  },
  {
   "cell_type": "code",
   "execution_count": 36,
   "metadata": {},
   "outputs": [
    {
     "data": {
      "text/plain": [
       "(<cell at 0x0000028B8EE35738: int object at 0x000000005AC78070>,\n",
       " <cell at 0x0000028B8EE35A68: int object at 0x000000005AC78090>)"
      ]
     },
     "execution_count": 36,
     "metadata": {},
     "output_type": "execute_result"
    }
   ],
   "source": [
    "getattr(w,'__closure__')"
   ]
  },
  {
   "cell_type": "code",
   "execution_count": 38,
   "metadata": {},
   "outputs": [
    {
     "data": {
      "text/plain": [
       "['__class__',\n",
       " '__delattr__',\n",
       " '__dir__',\n",
       " '__doc__',\n",
       " '__eq__',\n",
       " '__format__',\n",
       " '__ge__',\n",
       " '__getattribute__',\n",
       " '__gt__',\n",
       " '__hash__',\n",
       " '__init__',\n",
       " '__init_subclass__',\n",
       " '__le__',\n",
       " '__lt__',\n",
       " '__ne__',\n",
       " '__new__',\n",
       " '__reduce__',\n",
       " '__reduce_ex__',\n",
       " '__repr__',\n",
       " '__setattr__',\n",
       " '__sizeof__',\n",
       " '__str__',\n",
       " '__subclasshook__',\n",
       " 'co_argcount',\n",
       " 'co_cellvars',\n",
       " 'co_code',\n",
       " 'co_consts',\n",
       " 'co_filename',\n",
       " 'co_firstlineno',\n",
       " 'co_flags',\n",
       " 'co_freevars',\n",
       " 'co_kwonlyargcount',\n",
       " 'co_lnotab',\n",
       " 'co_name',\n",
       " 'co_names',\n",
       " 'co_nlocals',\n",
       " 'co_stacksize',\n",
       " 'co_varnames']"
      ]
     },
     "execution_count": 38,
     "metadata": {},
     "output_type": "execute_result"
    }
   ],
   "source": [
    "dir(getattr(w, '__code__'))"
   ]
  },
  {
   "cell_type": "code",
   "execution_count": 28,
   "metadata": {},
   "outputs": [
    {
     "data": {
      "text/plain": [
       "tuple"
      ]
     },
     "execution_count": 28,
     "metadata": {},
     "output_type": "execute_result"
    }
   ],
   "source": [
    "type(getattr(w,'__closure__'))"
   ]
  },
  {
   "cell_type": "code",
   "execution_count": 29,
   "metadata": {},
   "outputs": [
    {
     "data": {
      "text/plain": [
       "cell"
      ]
     },
     "execution_count": 29,
     "metadata": {},
     "output_type": "execute_result"
    }
   ],
   "source": [
    "type(getattr(w,'__closure__')[0])"
   ]
  },
  {
   "cell_type": "code",
   "execution_count": 32,
   "metadata": {},
   "outputs": [
    {
     "data": {
      "text/plain": [
       "['__class__',\n",
       " '__delattr__',\n",
       " '__dir__',\n",
       " '__doc__',\n",
       " '__eq__',\n",
       " '__format__',\n",
       " '__ge__',\n",
       " '__getattribute__',\n",
       " '__gt__',\n",
       " '__hash__',\n",
       " '__init__',\n",
       " '__init_subclass__',\n",
       " '__le__',\n",
       " '__lt__',\n",
       " '__ne__',\n",
       " '__new__',\n",
       " '__reduce__',\n",
       " '__reduce_ex__',\n",
       " '__repr__',\n",
       " '__setattr__',\n",
       " '__sizeof__',\n",
       " '__str__',\n",
       " '__subclasshook__',\n",
       " 'cell_contents']"
      ]
     },
     "execution_count": 32,
     "metadata": {},
     "output_type": "execute_result"
    }
   ],
   "source": [
    "dir(getattr(w,'__closure__')[0])"
   ]
  },
  {
   "cell_type": "code",
   "execution_count": 34,
   "metadata": {},
   "outputs": [
    {
     "data": {
      "text/plain": [
       "2"
      ]
     },
     "execution_count": 34,
     "metadata": {},
     "output_type": "execute_result"
    }
   ],
   "source": [
    "getattr(getattr(w,'__closure__')[1], 'cell_contents')"
   ]
  },
  {
   "cell_type": "code",
   "execution_count": 39,
   "metadata": {},
   "outputs": [
    {
     "name": "stdout",
     "output_type": "stream",
     "text": [
      "  2           0 LOAD_FAST                0 (func)\n",
      "              2 LOAD_FAST                1 (a)\n",
      "              4 LOAD_FAST                2 (b)\n",
      "              6 CALL_FUNCTION            2\n",
      "              8 LOAD_FAST                3 (c)\n",
      "             10 LOAD_CONST               1 (0)\n",
      "             12 STORE_SUBSCR\n",
      "             14 LOAD_CONST               0 (None)\n",
      "             16 RETURN_VALUE\n"
     ]
    }
   ],
   "source": [
    "def lambda_use(func,a,b,c):\n",
    "    c[0] = func(a,b)\n",
    "import dis\n",
    "dis.dis(lambda_use)"
   ]
  },
  {
   "cell_type": "code",
   "execution_count": 42,
   "metadata": {},
   "outputs": [
    {
     "data": {
      "text/plain": [
       "int"
      ]
     },
     "execution_count": 42,
     "metadata": {},
     "output_type": "execute_result"
    }
   ],
   "source": [
    "type(getattr(getattr(lambda_use, '__code__'), 'co_consts')[1])"
   ]
  },
  {
   "cell_type": "code",
   "execution_count": 46,
   "metadata": {},
   "outputs": [
    {
     "data": {
      "text/plain": [
       "NoneType"
      ]
     },
     "execution_count": 46,
     "metadata": {},
     "output_type": "execute_result"
    }
   ],
   "source": [
    "def func():\n",
    "    return 42\n",
    "type(getattr(func, '__closure__'))"
   ]
  },
  {
   "cell_type": "code",
   "execution_count": 47,
   "metadata": {},
   "outputs": [
    {
     "name": "stdout",
     "output_type": "stream",
     "text": [
      "42\n",
      "72\n"
     ]
    }
   ],
   "source": [
    "def func(x,y):\n",
    "    return lambda a,b: y[0]+x\n",
    "\n",
    "d = [30]\n",
    "z = func(12,d)\n",
    "print(z(1,2))\n",
    "\n",
    "d[0] = 60\n",
    "print(z(1,2))"
   ]
  },
  {
   "cell_type": "code",
   "execution_count": 52,
   "metadata": {},
   "outputs": [
    {
     "data": {
      "text/plain": [
       "int"
      ]
     },
     "execution_count": 52,
     "metadata": {},
     "output_type": "execute_result"
    }
   ],
   "source": [
    "type(getattr(getattr(z,'__closure__')[0], 'cell_contents'))"
   ]
  },
  {
   "cell_type": "markdown",
   "metadata": {},
   "source": [
    "# Intrinsics"
   ]
  },
  {
   "cell_type": "code",
   "execution_count": 15,
   "metadata": {},
   "outputs": [
    {
     "data": {
      "text/plain": [
       "['__call__',\n",
       " '__class__',\n",
       " '__delattr__',\n",
       " '__dict__',\n",
       " '__dir__',\n",
       " '__doc__',\n",
       " '__eq__',\n",
       " '__format__',\n",
       " '__ge__',\n",
       " '__getattribute__',\n",
       " '__gt__',\n",
       " '__hash__',\n",
       " '__hybrid_cuda__intrinsic_function__',\n",
       " '__init__',\n",
       " '__init_subclass__',\n",
       " '__le__',\n",
       " '__lt__',\n",
       " '__module__',\n",
       " '__ne__',\n",
       " '__new__',\n",
       " '__reduce__',\n",
       " '__reduce_ex__',\n",
       " '__repr__',\n",
       " '__setattr__',\n",
       " '__sizeof__',\n",
       " '__str__',\n",
       " '__subclasshook__',\n",
       " '__weakref__',\n",
       " 'func']"
      ]
     },
     "execution_count": 15,
     "metadata": {},
     "output_type": "execute_result"
    }
   ],
   "source": [
    "class intrinsic_function_class(object):\n",
    "    __hybrid_cuda__func__ = None\n",
    "    __hybrid_cuda__intrinsic_function__ = ''\n",
    "    def __init__(self, func, intrinsic):\n",
    "        self.__hybrid_cuda__func__ = func\n",
    "        self.__hybrid_cuda__intrinsic_function__ = intrinsic\n",
    "\n",
    "    def __call__(self, *args):\n",
    "        return self.__hybrid_cuda__func__(*args)\n",
    "\n",
    "\n",
    "def intrinsic_function(intrinsicname):\n",
    "    def decorator(func):\n",
    "        return intrinsic_function_class(func, intrinsicname)\n",
    "    return decorator\n",
    "\n",
    "class intrinsic_constant_class(object):\n",
    "    __hybrid_cuda__func__ = None\n",
    "    __hybrid_cuda__intrinsic_constant__ = ''\n",
    "    def __init__(self, func, intrinsic):\n",
    "        self.__hybrid_cuda__func__ = func\n",
    "        self.__hybrid_cuda__intrinsic_constant__ = intrinsic\n",
    "\n",
    "    def __call__(self, *args):\n",
    "        return self.__hybrid_cuda__func__(*args)\n",
    "\n",
    "\n",
    "def intrinsic_constant(intrinsicname):\n",
    "    def decorator(func):\n",
    "        return intrinsic_constant_class(func, intrinsicname)\n",
    "    return decorator\n",
    "\n",
    "@intrinsic_function('__syncthreads')\n",
    "def __syncthreads():\n",
    "    pass\n",
    "\n"
   ]
  },
  {
   "cell_type": "code",
   "execution_count": 13,
   "metadata": {},
   "outputs": [
    {
     "data": {
      "text/plain": [
       "type"
      ]
     },
     "execution_count": 13,
     "metadata": {},
     "output_type": "execute_result"
    }
   ],
   "source": [
    "def func():\n",
    "    pass\n",
    "\n",
    "type(object)"
   ]
  },
  {
   "cell_type": "code",
   "execution_count": 16,
   "metadata": {},
   "outputs": [],
   "source": [
    "def __syncthreads() -> None:\n",
    "    pass"
   ]
  },
  {
   "cell_type": "code",
   "execution_count": 19,
   "metadata": {},
   "outputs": [
    {
     "data": {
      "text/plain": [
       "{'return': None}"
      ]
     },
     "execution_count": 19,
     "metadata": {},
     "output_type": "execute_result"
    }
   ],
   "source": [
    "getattr(__syncthreads,'__annotations__')"
   ]
  },
  {
   "cell_type": "code",
   "execution_count": 20,
   "metadata": {},
   "outputs": [
    {
     "data": {
      "text/plain": [
       "NoneType"
      ]
     },
     "execution_count": 20,
     "metadata": {},
     "output_type": "execute_result"
    }
   ],
   "source": [
    "type(getattr(__syncthreads,'__annotations__')['return'])"
   ]
  },
  {
   "cell_type": "code",
   "execution_count": 21,
   "metadata": {},
   "outputs": [
    {
     "name": "stdout",
     "output_type": "stream",
     "text": [
      "  2           0 LOAD_GLOBAL              0 (threadIdx)\n",
      "              2 LOAD_ATTR                1 (x)\n",
      "              4 LOAD_FAST                0 (d)\n",
      "              6 LOAD_CONST               1 (0)\n",
      "              8 STORE_SUBSCR\n",
      "             10 LOAD_CONST               0 (None)\n",
      "             12 RETURN_VALUE\n"
     ]
    }
   ],
   "source": [
    "def getthreadidx(d):\n",
    "    d[0] = threadIdx.x\n",
    "    \n",
    "import dis\n",
    "dis.dis(getthreadidx)"
   ]
  },
  {
   "cell_type": "code",
   "execution_count": 26,
   "metadata": {},
   "outputs": [
    {
     "data": {
      "text/plain": [
       "['__class__',\n",
       " '__delattr__',\n",
       " '__dir__',\n",
       " '__doc__',\n",
       " '__eq__',\n",
       " '__format__',\n",
       " '__ge__',\n",
       " '__getattribute__',\n",
       " '__gt__',\n",
       " '__hash__',\n",
       " '__init__',\n",
       " '__init_subclass__',\n",
       " '__le__',\n",
       " '__lt__',\n",
       " '__ne__',\n",
       " '__new__',\n",
       " '__reduce__',\n",
       " '__reduce_ex__',\n",
       " '__repr__',\n",
       " '__setattr__',\n",
       " '__sizeof__',\n",
       " '__str__',\n",
       " '__subclasshook__',\n",
       " 'co_argcount',\n",
       " 'co_cellvars',\n",
       " 'co_code',\n",
       " 'co_consts',\n",
       " 'co_filename',\n",
       " 'co_firstlineno',\n",
       " 'co_flags',\n",
       " 'co_freevars',\n",
       " 'co_kwonlyargcount',\n",
       " 'co_lnotab',\n",
       " 'co_name',\n",
       " 'co_names',\n",
       " 'co_nlocals',\n",
       " 'co_stacksize',\n",
       " 'co_varnames']"
      ]
     },
     "execution_count": 26,
     "metadata": {},
     "output_type": "execute_result"
    }
   ],
   "source": [
    "dir(getattr(getthreadidx,'__code__'))"
   ]
  },
  {
   "cell_type": "code",
   "execution_count": 28,
   "metadata": {},
   "outputs": [
    {
     "data": {
      "text/plain": [
       "('threadIdx', 'x')"
      ]
     },
     "execution_count": 28,
     "metadata": {},
     "output_type": "execute_result"
    }
   ],
   "source": [
    "getattr(getattr(getthreadidx,'__code__'), 'co_names')"
   ]
  },
  {
   "cell_type": "code",
   "execution_count": 30,
   "metadata": {},
   "outputs": [],
   "source": [
    "class threadIdx(object):\n",
    "    __hybrid_cuda__intrinsic_type__ = \"threadIdx\"\n",
    "    x : int = 0\n",
    "    y = 0\n",
    "    z = 0"
   ]
  },
  {
   "cell_type": "code",
   "execution_count": 31,
   "metadata": {},
   "outputs": [
    {
     "data": {
      "text/plain": [
       "{'x': int}"
      ]
     },
     "execution_count": 31,
     "metadata": {},
     "output_type": "execute_result"
    }
   ],
   "source": [
    "getattr(threadIdx,'__annotations__')"
   ]
  },
  {
   "cell_type": "code",
   "execution_count": 32,
   "metadata": {},
   "outputs": [
    {
     "data": {
      "text/plain": [
       "type"
      ]
     },
     "execution_count": 32,
     "metadata": {},
     "output_type": "execute_result"
    }
   ],
   "source": [
    "type(threadIdx)"
   ]
  },
  {
   "cell_type": "code",
   "execution_count": 63,
   "metadata": {},
   "outputs": [
    {
     "data": {
      "text/plain": [
       "'int'"
      ]
     },
     "execution_count": 63,
     "metadata": {},
     "output_type": "execute_result"
    }
   ],
   "source": [
    "a = 42\n",
    "getattr(type(a), '__qualname__')"
   ]
  },
  {
   "cell_type": "code",
   "execution_count": 46,
   "metadata": {},
   "outputs": [
    {
     "data": {
      "text/plain": [
       "__main__.threadIdx"
      ]
     },
     "execution_count": 46,
     "metadata": {},
     "output_type": "execute_result"
    }
   ],
   "source": [
    "a = threadIdx()\n",
    "type(a)"
   ]
  },
  {
   "cell_type": "code",
   "execution_count": 61,
   "metadata": {},
   "outputs": [
    {
     "data": {
      "text/plain": [
       "'threadIdx'"
      ]
     },
     "execution_count": 61,
     "metadata": {},
     "output_type": "execute_result"
    }
   ],
   "source": [
    "getattr(type(a), '__qualname__')"
   ]
  },
  {
   "cell_type": "code",
   "execution_count": 60,
   "metadata": {},
   "outputs": [
    {
     "data": {
      "text/plain": [
       "['__annotations__',\n",
       " '__class__',\n",
       " '__delattr__',\n",
       " '__dict__',\n",
       " '__dir__',\n",
       " '__doc__',\n",
       " '__eq__',\n",
       " '__format__',\n",
       " '__ge__',\n",
       " '__getattribute__',\n",
       " '__gt__',\n",
       " '__hash__',\n",
       " '__hybrid_cuda__intrinsic_type__',\n",
       " '__init__',\n",
       " '__init_subclass__',\n",
       " '__le__',\n",
       " '__lt__',\n",
       " '__module__',\n",
       " '__ne__',\n",
       " '__new__',\n",
       " '__reduce__',\n",
       " '__reduce_ex__',\n",
       " '__repr__',\n",
       " '__setattr__',\n",
       " '__sizeof__',\n",
       " '__str__',\n",
       " '__subclasshook__',\n",
       " '__weakref__',\n",
       " 'x',\n",
       " 'y',\n",
       " 'z']"
      ]
     },
     "execution_count": 60,
     "metadata": {},
     "output_type": "execute_result"
    }
   ],
   "source": [
    "dir(type(a))"
   ]
  },
  {
   "cell_type": "code",
   "execution_count": 64,
   "metadata": {},
   "outputs": [],
   "source": [
    "def answer() -> int:\n",
    "    return 42"
   ]
  },
  {
   "cell_type": "code",
   "execution_count": 66,
   "metadata": {},
   "outputs": [
    {
     "data": {
      "text/plain": [
       "'int'"
      ]
     },
     "execution_count": 66,
     "metadata": {},
     "output_type": "execute_result"
    }
   ],
   "source": [
    "answer.__annotations__['return'].__qualname__"
   ]
  },
  {
   "cell_type": "code",
   "execution_count": null,
   "metadata": {},
   "outputs": [],
   "source": []
  }
 ],
 "metadata": {
  "kernelspec": {
   "display_name": "Python 3",
   "language": "python",
   "name": "python3"
  },
  "language_info": {
   "codemirror_mode": {
    "name": "ipython",
    "version": 3
   },
   "file_extension": ".py",
   "mimetype": "text/x-python",
   "name": "python",
   "nbconvert_exporter": "python",
   "pygments_lexer": "ipython3",
   "version": "3.6.5"
  }
 },
 "nbformat": 4,
 "nbformat_minor": 2
}
